entrypoint/__init__.py
entrypoint/args.py
entrypoint/catalog.py
entrypoint/config.py
entrypoint/exceptions.py
entrypoint/utils.py
entrypoint/tests/__init__.py
entrypoint/tests/test_entrypoint.py
python_entrypoint-0.1.3.dist-info/DESCRIPTION.rst
python_entrypoint-0.1.3.dist-info/METADATA
python_entrypoint-0.1.3.dist-info/RECORD
python_entrypoint-0.1.3.dist-info/WHEEL
python_entrypoint-0.1.3.dist-info/entry_points.txt
python_entrypoint-0.1.3.dist-info/metadata.json
python_entrypoint-0.1.3.dist-info/pbr.json
python_entrypoint-0.1.3.dist-info/top_level.txt
