Metadata-Version: 2.0
Name: python-entrypoint
Version: 0.1.3
Summary: An entrypoint for containers
Home-page: http://github.com/seecloud/entrypoint
Author: Mirantis Inc.
Author-email: ikharin@mirantis.com
License: Apache 2.0
Platform: any
Classifier: Environment :: Console
Classifier: Intended Audience :: Developers
Classifier: License :: OSI Approved :: Apache Software License
Classifier: Operating System :: POSIX :: Linux
Classifier: Programming Language :: Python
Classifier: Programming Language :: Python :: 2
Classifier: Programming Language :: Python :: 2.7
Classifier: Programming Language :: Python :: 3
Classifier: Programming Language :: Python :: 3.4
Classifier: Programming Language :: Python :: 3.5
Requires-Dist: pbr (>=1.6)
Requires-Dist: python-etcd (>=0.4.3)
Requires-Dist: six (>=1.9.0)
